{
  "input_pdf": "/Users/averrik/Cloud/github/tito/tests/smoke/fixtures/WSP_2024a_LOU TSF Site-Specific Seismic Hazard Assessment.pdf",
  "prepared_pdf": "/Users/averrik/Cloud/github/garage/pdf/sessions/run-20260129_135033/WSP_2024a_LOU_TSF_Site-Specific_Seismic_Hazard_Assessment.prepared.pdf",
  "ocr_pdf": "/Users/averrik/Cloud/github/garage/pdf/sessions/run-20260129_135033/WSP_2024a_LOU_TSF_Site-Specific_Seismic_Hazard_Assessment.ocr.pdf",
  "ocr_ran": false,
  "tables": [
    {
      "index": 1,
      "page": 8,
      "tool": "pymupdf",
      "mode": "pymupdf/lines/lines",
      "sha1": "594b9d80156066625f7e5fcd6b0bb2e9a07f5ae7",
      "rows": 15,
      "cols": 8,
      "cells_total": 120,
      "cells_nonempty": 97,
      "empty_ratio": 0.1917,
      "digit_ratio": 0.9278,
      "bbox": [
        54.14071884155273,
        118.2859893798828,
        557.9656192555148,
        402.7645180442116
      ],
      "width_ratio": 0.8232,
      "height_ratio": 0.3592,
      "area_ratio": 0.2957,
      "top_ratio": 0.1494,
      "bottom_ratio": 0.5085
    },
    {
      "index": 2,
      "page": 10,
      "tool": "pymupdf",
      "mode": "pymupdf/lines/lines",
      "sha1": "76044d3711392dcd062ab4c80b4602b974f4f7ff",
      "rows": 21,
      "cols": 6,
      "cells_total": 126,
      "cells_nonempty": 32,
      "empty_ratio": 0.746,
      "digit_ratio": 0.0625,
      "bbox": [
        54.187358703613285,
        177.31339518229166,
        541.31427734375,
        481.2999801635742
      ],
      "width_ratio": 0.796,
      "height_ratio": 0.3838,
      "area_ratio": 0.3055,
      "top_ratio": 0.2239,
      "bottom_ratio": 0.6077
    }
  ]
}
